es2/verilog/fsm.v
module detector (x,,clk,rst,z);
    input x;
    input clk; 
    input rst;
    output z;

    reg z;
    reg [2:0] c_state;
    reg [2:0] n_state;
    
    parameter IDLE = 3'b000, S0 = 3'b001, S1 = 3'b010, S01 = 3'b011, S10 = 3'b100, S11 = 3'b101;
    
    always @(posedge clk) begin 
        if (rst == 1) 
            c_state <= IDLE;
        else
            c_state <= n_state;
    end

    always @(c_state, x) begin
        case (c_state)
            IDLE: begin
                z = 0;
                if (x == 1) begin
                    n_state = S1;
                end else begin
                    n_state = IDLE;
                end
            end
            S1: begin
                z = 0;
                if (x == 1) begin
                    n_state = S1;
                end else begin 
                    n_state = S10;
                end
            end
            S10: begin
                z = 1;
                if (x == 1) begin
                    n_state = S01;
                end else begin 
                    n_state = S0;
                end
            end
            S01: begin
                z = 1;
                if (x == 1) begin
                    n_state = S1;
                end else begin 
                    n_state = S10;
                end
            end
            default: begin
                n_state = IDLE;
                z = 0;
            end
        endcase
    end
endmodule

es2/verilog/fsm_tb.v
`timescale 1ns / 1ps
`include "fsm.v"

module fsm_tb;

    // Inputs
    reg x;
    reg clk;
    reg rst;

    // Outputs
    wire z;

    // Instantiate the Unit Under Test (UUT)
    detector uut (
        .x(x), 
        .clk(clk), 
        .rst(rst),
        .z(z) 
    );

    `define assert(signal, value) \
        if (signal !== value) begin \
            $display("ASSERTION FAILED in %m: signal != value"); \
            $finish; \
        end


    initial begin

        $dumpfile("fsm_tb.vcd");
        $dumpvars(0, fsm_tb);

        // Initialize Inputs
        x = 0;
        clk = 0;
        rst = 0;

        // Reset the design
        rst = 1;
        #10;
        rst = 0;
        
        // Inizio della sequenza di test
        // I valori di 'x' vengono cambiati al fronte di discesa del clock
        // per evitare race condition.
        @(negedge clk) x = 1;
        @(negedge clk) x = 0;
        @(negedge clk) x = 1;
        @(negedge clk) x = 1;
        @(negedge clk) x = 0;
        @(negedge clk) x = 0;
        @(negedge clk) x = 1;
        @(negedge clk) x = 0;

        // Finish simulation
        $finish;
    end

    // Clock generation
    always #5 clk = ~clk;

endmodule

es2/verilog/fsm_tb.vcd
$date
	Fri Sep 19 13:18:56 2025
$end
$version
	Icarus Verilog
$end
$timescale
	1ps
$end
$scope module fsm_tb $end
$var wire 1 ! z $end
$var reg 1 " clk $end
$var reg 1 # rst $end
$var reg 1 $ x $end
$scope module uut $end
$var wire 1 " clk $end
$var wire 1 # rst $end
$var wire 1 $ x $end
$var parameter 3 % IDLE $end
$var parameter 3 & S0 $end
$var parameter 3 ' S01 $end
$var parameter 3 ( S1 $end
$var parameter 3 ) S10 $end
$var parameter 3 * S11 $end
$var reg 3 + c_state [2:0] $end
$var reg 3 , n_state [2:0] $end
$var reg 1 ! z $end
$upscope $end
$upscope $end
$enddefinitions $end
$comment Show the parameter values. $end
$dumpall
b101 *
b100 )
b10 (
b11 '
b1 &
b0 %
$end
#0
$dumpvars
b0 ,
bx +
0$
1#
0"
0!
$end
#5000
b0 +
1"
#10000
b10 ,
1$
0"
0#
#15000
b10 +
1"
#20000
b100 ,
0$
0"
#25000
b1 ,
1!
b100 +
1"
#30000
b11 ,
1$
0"
#35000
b10 ,
b11 +
1"
#40000
0"
#45000
0!
b10 +
1"
#50000
b100 ,
0$
0"
#55000
b1 ,
1!
b100 +
1"
#60000
0"
#65000
0!
b0 ,
b1 +
1"
#70000
1$
0"
#75000
b10 ,
b0 +
1"
#80000
b0 ,
0$
0"
